numcodecs-0.16.3.dist-info/RECORD
numcodecs-0.16.3.dist-info/WHEEL
numcodecs-0.16.3.dist-info/entry_points.txt
numcodecs-0.16.3.dist-info/top_level.txt
numcodecs-0.16.3.dist-info/METADATA
numcodecs-0.16.3.dist-info/licenses/LICENSE.txt
numcodecs-0.16.3.dist-info/licenses/c-blosc/LICENSE.txt
numcodecs-0.16.3.dist-info/licenses/c-blosc/LICENSES/SNAPPY.txt
numcodecs-0.16.3.dist-info/licenses/c-blosc/LICENSES/FASTLZ.txt
numcodecs-0.16.3.dist-info/licenses/c-blosc/LICENSES/ZLIB.txt
numcodecs-0.16.3.dist-info/licenses/c-blosc/LICENSES/BITSHUFFLE.txt
numcodecs-0.16.3.dist-info/licenses/c-blosc/LICENSES/ZLIB-NG.txt
numcodecs-0.16.3.dist-info/licenses/c-blosc/LICENSES/LZ4.txt
numcodecs-0.16.3.dist-info/licenses/c-blosc/LICENSES/STDINT.txt
numcodecs/blosc.cpython-313-darwin.so
numcodecs/lzma.py
numcodecs/astype.py
numcodecs/gzip.py
numcodecs/lz4.cpython-313-darwin.so
numcodecs/base64.py
numcodecs/bz2.py
numcodecs/version.py
numcodecs/compat.py
numcodecs/checksum32.py
numcodecs/vlen.cpython-313-darwin.so
numcodecs/ndarray_like.py
numcodecs/quantize.py
numcodecs/registry.py
numcodecs/jenkins.cpython-313-darwin.so
numcodecs/pickles.py
numcodecs/zstd.cpython-313-darwin.so
numcodecs/fixedscaleoffset.py
numcodecs/__init__.py
numcodecs/bitround.py
numcodecs/_shuffle.cpython-313-darwin.so
numcodecs/zlib.py
numcodecs/shuffle.py
numcodecs/fletcher32.cpython-313-darwin.so
numcodecs/compat_ext.cpython-313-darwin.so
numcodecs/zarr3.py
numcodecs/delta.py
numcodecs/zfpy.py
numcodecs/msgpacks.py
numcodecs/errors.py
numcodecs/packbits.py
numcodecs/categorize.py
numcodecs/json.py
numcodecs/abc.py
numcodecs/pcodec.py
numcodecs/tests/test_categorize.py
numcodecs/tests/test_registry.py
numcodecs/tests/test_vlen_utf8.py
numcodecs/tests/test_bitround.py
numcodecs/tests/test_gzip.py
numcodecs/tests/test_zarr3.py
numcodecs/tests/test_delta.py
numcodecs/tests/test_lzma.py
numcodecs/tests/test_bz2.py
numcodecs/tests/__init__.py
numcodecs/tests/test_pickles.py
numcodecs/tests/test_quantize.py
numcodecs/tests/test_entrypoints_backport.py
numcodecs/tests/test_pcodec.py
numcodecs/tests/test_lz4.py
numcodecs/tests/test_msgpacks.py
numcodecs/tests/test_astype.py
numcodecs/tests/test_jenkins.py
numcodecs/tests/test_fletcher32.py
numcodecs/tests/test_packbits.py
numcodecs/tests/common.py
numcodecs/tests/test_base64.py
numcodecs/tests/test_shuffle.py
numcodecs/tests/test_fixedscaleoffset.py
numcodecs/tests/test_compat.py
numcodecs/tests/test_pyzstd.py
numcodecs/tests/test_zlib.py
numcodecs/tests/test_json.py
numcodecs/tests/test_ndarray_like.py
numcodecs/tests/test_vlen_array.py
numcodecs/tests/test_zstd.py
numcodecs/tests/test_vlen_bytes.py
numcodecs/tests/package_with_entrypoint-0.1.dist-info/entry_points.txt
